{
    "fluentMethods": true,
    "relationships": [],
    "fields": [
        {
            "fieldName": "address1",
            "fieldType": "String",
            "fieldValidateRules": [
                "required"
            ]
        },
        {
            "fieldName": "address2",
            "fieldType": "String"
        },
        {
            "fieldName": "address3",
            "fieldType": "String"
        },
        {
            "fieldName": "city",
            "fieldType": "String",
            "fieldValidateRules": [
                "required"
            ]
        },
        {
            "fieldName": "state",
            "fieldType": "String"
        },
        {
            "fieldName": "country",
            "fieldType": "String"
        },
        {
            "fieldName": "latitude",
            "fieldType": "String"
        },
        {
            "fieldName": "longitude",
            "fieldType": "String"
        }
    ],
    "changelogDate": "20170302141944",
    "entityTableName": "location",
    "dto": "mapstruct",
    "pagination": "pagination",
    "service": "serviceImpl"
}